[
    {
      "id": 1,
      "title": "IIIT Sonepat HacktoberFest Meetup",
      "time": "October 22' 2021  @  5:30PM",
      "location": "Virtual",
      "imagelink": "collab.png",
      "formatDate": "17-10-2020",
      "name":" ",
      "company":" "
    },
    {
        "id": 2,
        "title": "Title here",
        "name": "Brian Douglas",
        "time": "October 22' 2021  @  6:00PM",
        "location": "Virtual",
        "imagelink": "https://d33wubrfki0l68.cloudfront.net/ced071bb56f55694eeb9d01d3c0a35d3b561d38d/f3fb2/img/brian.jpg",
        "formatDate": "17-10-2020",
        "company": "Github"
    },
    {
      "id": 3,
      "title": "Title Here",
      "name": "Rizel Scarlett",
      "time": "October 22' 2021  @  7:00PM",
      "location": "Virtual",
      "imagelink": "https://media-exp1.licdn.com/dms/image/C4E03AQE4ekWo_AxCMg/profile-displayphoto-shrink_200_200/0/1551287106903?e=1639612800&v=beta&t=bsQgqHGmDK7n7Gk_0uuCQC9F6jTBfgJIqyHhR_wG7O8",
      "formatDate": "17-10-2020",
      "company": "Github"
    },
    {
        "id":4,
        "title": "Title Here",
        "name": "Aditya Oberai",
        "time":"October 22' 2021 @ 6:30PM",
        "location":"Virtual",
        "imagelink": "https://media-exp1.licdn.com/dms/image/C4E03AQHHeOt8RFiMGA/profile-displayphoto-shrink_200_200/0/1621757822139?e=1639612800&v=beta&t=PRqL2EKZbUcrnBscuUeo-26nMsUxYKAiXeqYKML8szg",
        "formatDate":"18-10-2020",
        "company": "Appwrite"
    }
  ]
  
